{
    "id": "ocf",
    "version": 1,
    "status": "proposed",
    "name": "Ocf",
    "ephemeral": false,
    "attributes": {
        "st": {
            "schema": {
                "title": "StringAttribute",
                "type": "object",
                "properties": {
                    "value": {
                        "title": "String",
                        "type": "string",
                        "maxLength": 255
                    }
                },
                "additionalProperties": false,
                "required": [
                    "value"
                ]
            },
            "enumCommands": []
        },
        "mndt": {
            "schema": {
                "title": "StringAttribute",
                "type": "object",
                "properties": {
                    "value": {
                        "title": "String",
                        "type": "string",
                        "maxLength": 255
                    }
                },
                "additionalProperties": false,
                "required": [
                    "value"
                ]
            },
            "enumCommands": []
        },
        "mnfv": {
            "schema": {
                "title": "StringAttribute",
                "type": "object",
                "properties": {
                    "value": {
                        "title": "String",
                        "type": "string",
                        "maxLength": 255
                    }
                },
                "additionalProperties": false,
                "required": [
                    "value"
                ]
            },
            "enumCommands": []
        },
        "mnhw": {
            "schema": {
                "title": "StringAttribute",
                "type": "object",
                "properties": {
                    "value": {
                        "title": "String",
                        "type": "string",
                        "maxLength": 255
                    }
                },
                "additionalProperties": false,
                "required": [
                    "value"
                ]
            },
            "enumCommands": []
        },
        "di": {
            "schema": {
                "title": "StringAttribute",
                "type": "object",
                "properties": {
                    "value": {
                        "title": "String",
                        "type": "string",
                        "maxLength": 255
                    }
                },
                "additionalProperties": false,
                "required": [
                    "value"
                ]
            },
            "enumCommands": []
        },
        "mnsl": {
            "schema": {
                "title": "StringAttribute",
                "type": "object",
                "properties": {
                    "value": {
                        "title": "String",
                        "type": "string",
                        "maxLength": 255
                    }
                },
                "additionalProperties": false,
                "required": [
                    "value"
                ]
            },
            "enumCommands": []
        },
        "dmv": {
            "schema": {
                "title": "StringAttribute",
                "type": "object",
                "properties": {
                    "value": {
                        "title": "String",
                        "type": "string",
                        "maxLength": 255
                    }
                },
                "additionalProperties": false,
                "required": [
                    "value"
                ]
            },
            "enumCommands": []
        },
        "n": {
            "schema": {
                "title": "StringAttribute",
                "type": "object",
                "properties": {
                    "value": {
                        "title": "String",
                        "type": "string",
                        "maxLength": 255
                    }
                },
                "additionalProperties": false,
                "required": [
                    "value"
                ]
            },
            "enumCommands": []
        },
        "mnmo": {
            "schema": {
                "title": "StringAttribute",
                "type": "object",
                "properties": {
                    "value": {
                        "title": "String",
                        "type": "string",
                        "maxLength": 255
                    }
                },
                "additionalProperties": false,
                "required": [
                    "value"
                ]
            },
            "enumCommands": []
        },
        "vid": {
            "schema": {
                "title": "StringAttribute",
                "type": "object",
                "properties": {
                    "value": {
                        "title": "String",
                        "type": "string",
                        "maxLength": 255
                    }
                },
                "additionalProperties": false,
                "required": [
                    "value"
                ]
            },
            "enumCommands": []
        },
        "mnmn": {
            "schema": {
                "title": "StringAttribute",
                "type": "object",
                "properties": {
                    "value": {
                        "title": "String",
                        "type": "string",
                        "maxLength": 255
                    }
                },
                "additionalProperties": false,
                "required": [
                    "value"
                ]
            },
            "enumCommands": []
        },
        "mnml": {
            "schema": {
                "title": "StringAttribute",
                "type": "object",
                "properties": {
                    "value": {
                        "title": "String",
                        "type": "string",
                        "maxLength": 255
                    }
                },
                "additionalProperties": false,
                "required": [
                    "value"
                ]
            },
            "enumCommands": []
        },
        "mnpv": {
            "schema": {
                "title": "StringAttribute",
                "type": "object",
                "properties": {
                    "value": {
                        "title": "String",
                        "type": "string",
                        "maxLength": 255
                    }
                },
                "additionalProperties": false,
                "required": [
                    "value"
                ]
            },
            "enumCommands": []
        },
        "mnos": {
            "schema": {
                "title": "StringAttribute",
                "type": "object",
                "properties": {
                    "value": {
                        "title": "String",
                        "type": "string",
                        "maxLength": 255
                    }
                },
                "additionalProperties": false,
                "required": [
                    "value"
                ]
            },
            "enumCommands": []
        },
        "pi": {
            "schema": {
                "title": "StringAttribute",
                "type": "object",
                "properties": {
                    "value": {
                        "title": "String",
                        "type": "string",
                        "maxLength": 255
                    }
                },
                "additionalProperties": false,
                "required": [
                    "value"
                ]
            },
            "enumCommands": []
        },
        "icv": {
            "schema": {
                "title": "StringAttribute",
                "type": "object",
                "properties": {
                    "value": {
                        "title": "String",
                        "type": "string",
                        "maxLength": 255
                    }
                },
                "additionalProperties": false,
                "required": [
                    "value"
                ]
            },
            "enumCommands": []
        }
    },
    "commands": {
        "postOcfCommand": {
            "name": "postOcfCommand",
            "arguments": [
                {
                    "name": "href",
                    "optional": false,
                    "schema": {
                        "title": "String",
                        "type": "string",
                        "maxLength": 255
                    }
                },
                {
                    "name": "value",
                    "optional": false,
                    "schema": {
                        "title": "JsonObject",
                        "type": "object"
                    }
                }
            ]
        }
    }
}