{
	"lat": 50.55,
	"lon": 8.43,
	"timezone": "Europe/Berlin",
	"timezone_offset": 7200,
	"current": {
		"dt": 1620604620,
		"sunrise": 1620618337,
		"sunset": 1620673188,
		"temp": 288.71,
		"feels_like": 288.04,
		"pressure": 1004,
		"humidity": 66,
		"dew_point": 282.39,
		"uvi": 0,
		"clouds": 96,
		"visibility": 10000,
		"wind_speed": 0.89,
		"wind_deg": 138,
		"wind_gust": 1.34,
		"weather": [
			{
				"id": 804,
				"main": "Clouds",
				"description": "overcast clouds",
				"icon": "04n"
			}
		]
	},
	"minutely": [
		{
			"dt": 1620604620,
			"precipitation": 0
		},
		{
			"dt": 1620604680,
			"precipitation": 0
		},
		{
			"dt": 1620604740,
			"precipitation": 0
		},
		{
			"dt": 1620604800,
			"precipitation": 0
		},
		{
			"dt": 1620604860,
			"precipitation": 0
		},
		{
			"dt": 1620604920,
			"precipitation": 0
		},
		{
			"dt": 1620604980,
			"precipitation": 0
		},
		{
			"dt": 1620605040,
			"precipitation": 0
		},
		{
			"dt": 1620605100,
			"precipitation": 0
		},
		{
			"dt": 1620605160,
			"precipitation": 0
		},
		{
			"dt": 1620605220,
			"precipitation": 0
		},
		{
			"dt": 1620605280,
			"precipitation": 0
		},
		{
			"dt": 1620605340,
			"precipitation": 0
		},
		{
			"dt": 1620605400,
			"precipitation": 0
		},
		{
			"dt": 1620605460,
			"precipitation": 0
		},
		{
			"dt": 1620605520,
			"precipitation": 0
		},
		{
			"dt": 1620605580,
			"precipitation": 0
		},
		{
			"dt": 1620605640,
			"precipitation": 0
		},
		{
			"dt": 1620605700,
			"precipitation": 0
		},
		{
			"dt": 1620605760,
			"precipitation": 0
		},
		{
			"dt": 1620605820,
			"precipitation": 0
		},
		{
			"dt": 1620605880,
			"precipitation": 0
		},
		{
			"dt": 1620605940,
			"precipitation": 0
		},
		{
			"dt": 1620606000,
			"precipitation": 0
		},
		{
			"dt": 1620606060,
			"precipitation": 0
		},
		{
			"dt": 1620606120,
			"precipitation": 0
		},
		{
			"dt": 1620606180,
			"precipitation": 0
		},
		{
			"dt": 1620606240,
			"precipitation": 0
		},
		{
			"dt": 1620606300,
			"precipitation": 0
		},
		{
			"dt": 1620606360,
			"precipitation": 0
		},
		{
			"dt": 1620606420,
			"precipitation": 0
		},
		{
			"dt": 1620606480,
			"precipitation": 0
		},
		{
			"dt": 1620606540,
			"precipitation": 0
		},
		{
			"dt": 1620606600,
			"precipitation": 0
		},
		{
			"dt": 1620606660,
			"precipitation": 0
		},
		{
			"dt": 1620606720,
			"precipitation": 0
		},
		{
			"dt": 1620606780,
			"precipitation": 0
		},
		{
			"dt": 1620606840,
			"precipitation": 0
		},
		{
			"dt": 1620606900,
			"precipitation": 0
		},
		{
			"dt": 1620606960,
			"precipitation": 0
		},
		{
			"dt": 1620607020,
			"precipitation": 0
		},
		{
			"dt": 1620607080,
			"precipitation": 0
		},
		{
			"dt": 1620607140,
			"precipitation": 0.107
		},
		{
			"dt": 1620607200,
			"precipitation": 0.115
		},
		{
			"dt": 1620607260,
			"precipitation": 0.1762
		},
		{
			"dt": 1620607320,
			"precipitation": 0.2374
		},
		{
			"dt": 1620607380,
			"precipitation": 0.2986
		},
		{
			"dt": 1620607440,
			"precipitation": 0.3598
		},
		{
			"dt": 1620607500,
			"precipitation": 0.421
		},
		{
			"dt": 1620607560,
			"precipitation": 0.421
		},
		{
			"dt": 1620607620,
			"precipitation": 0.421
		},
		{
			"dt": 1620607680,
			"precipitation": 0.421
		},
		{
			"dt": 1620607740,
			"precipitation": 0.421
		},
		{
			"dt": 1620607800,
			"precipitation": 0.421
		},
		{
			"dt": 1620607860,
			"precipitation": 0.3914
		},
		{
			"dt": 1620607920,
			"precipitation": 0.3618
		},
		{
			"dt": 1620607980,
			"precipitation": 0.3322
		},
		{
			"dt": 1620608040,
			"precipitation": 0.3026
		},
		{
			"dt": 1620608100,
			"precipitation": 0.273
		},
		{
			"dt": 1620608160,
			"precipitation": 0.2816
		},
		{
			"dt": 1620608220,
			"precipitation": 0.2902
		}
	],
	"hourly": [
		{
			"dt": 1620601200,
			"temp": 288.64,
			"feels_like": 288.1,
			"pressure": 1004,
			"humidity": 71,
			"dew_point": 283.41,
			"uvi": 0,
			"clouds": 96,
			"visibility": 10000,
			"wind_speed": 1.09,
			"wind_deg": 174,
			"wind_gust": 1.43,
			"weather": [
				{
					"id": 804,
					"main": "Clouds",
					"description": "overcast clouds",
					"icon": "04n"
				}
			],
			"pop": 0.68
		},
		{
			"dt": 1620604800,
			"temp": 288.71,
			"feels_like": 288.04,
			"pressure": 1004,
			"humidity": 66,
			"dew_point": 282.39,
			"uvi": 0,
			"clouds": 96,
			"visibility": 10000,
			"wind_speed": 1.08,
			"wind_deg": 197,
			"wind_gust": 1.43,
			"weather": [
				{
					"id": 804,
					"main": "Clouds",
					"description": "overcast clouds",
					"icon": "04n"
				}
			],
			"pop": 0.65
		},
		{
			"dt": 1620608400,
			"temp": 288.49,
			"feels_like": 287.93,
			"pressure": 1004,
			"humidity": 71,
			"dew_point": 283.27,
			"uvi": 0,
			"clouds": 97,
			"visibility": 10000,
			"wind_speed": 0.81,
			"wind_deg": 149,
			"wind_gust": 0.96,
			"weather": [
				{
					"id": 500,
					"main": "Rain",
					"description": "light rain",
					"icon": "10n"
				}
			],
			"pop": 0.22,
			"rain": {
				"1h": 0.32
			}
		},
		{
			"dt": 1620612000,
			"temp": 288.13,
			"feels_like": 287.67,
			"pressure": 1004,
			"humidity": 76,
			"dew_point": 283.94,
			"uvi": 0,
			"clouds": 98,
			"visibility": 10000,
			"wind_speed": 1.45,
			"wind_deg": 133,
			"wind_gust": 1.4,
			"weather": [
				{
					"id": 500,
					"main": "Rain",
					"description": "light rain",
					"icon": "10n"
				}
			],
			"pop": 0.2,
			"rain": {
				"1h": 0.75
			}
		},
		{
			"dt": 1620615600,
			"temp": 287.63,
			"feels_like": 287.27,
			"pressure": 1004,
			"humidity": 82,
			"dew_point": 284.6,
			"uvi": 0,
			"clouds": 98,
			"visibility": 10000,
			"wind_speed": 1.05,
			"wind_deg": 107,
			"wind_gust": 1.17,
			"weather": [
				{
					"id": 804,
					"main": "Clouds",
					"description": "overcast clouds",
					"icon": "04n"
				}
			],
			"pop": 0
		},
		{
			"dt": 1620619200,
			"temp": 286.55,
			"feels_like": 286.24,
			"pressure": 1005,
			"humidity": 88,
			"dew_point": 284.61,
			"uvi": 0,
			"clouds": 96,
			"visibility": 10000,
			"wind_speed": 1.25,
			"wind_deg": 208,
			"wind_gust": 1.28,
			"weather": [
				{
					"id": 804,
					"main": "Clouds",
					"description": "overcast clouds",
					"icon": "04d"
				}
			],
			"pop": 0.01
		},
		{
			"dt": 1620622800,
			"temp": 287.06,
			"feels_like": 286.96,
			"pressure": 1007,
			"humidity": 94,
			"dew_point": 285.55,
			"uvi": 0.15,
			"clouds": 97,
			"visibility": 10000,
			"wind_speed": 1.8,
			"wind_deg": 206,
			"wind_gust": 2.68,
			"weather": [
				{
					"id": 804,
					"main": "Clouds",
					"description": "overcast clouds",
					"icon": "04d"
				}
			],
			"pop": 0.02
		},
		{
			"dt": 1620626400,
			"temp": 288.93,
			"feels_like": 288.94,
			"pressure": 1007,
			"humidity": 91,
			"dew_point": 286.94,
			"uvi": 0.49,
			"clouds": 97,
			"visibility": 10000,
			"wind_speed": 0.87,
			"wind_deg": 160,
			"wind_gust": 3.87,
			"weather": [
				{
					"id": 500,
					"main": "Rain",
					"description": "light rain",
					"icon": "10d"
				}
			],
			"pop": 0.33,
			"rain": {
				"1h": 0.2
			}
		},
		{
			"dt": 1620630000,
			"temp": 288.38,
			"feels_like": 288.44,
			"pressure": 1007,
			"humidity": 95,
			"dew_point": 286.95,
			"uvi": 0.19,
			"clouds": 100,
			"visibility": 10000,
			"wind_speed": 1.81,
			"wind_deg": 261,
			"wind_gust": 4.32,
			"weather": [
				{
					"id": 500,
					"main": "Rain",
					"description": "light rain",
					"icon": "10d"
				}
			],
			"pop": 0.47,
			"rain": {
				"1h": 0.17
			}
		},
		{
			"dt": 1620633600,
			"temp": 288.58,
			"feels_like": 288.55,
			"pressure": 1008,
			"humidity": 91,
			"dew_point": 286.47,
			"uvi": 0.34,
			"clouds": 100,
			"visibility": 10000,
			"wind_speed": 3.23,
			"wind_deg": 249,
			"wind_gust": 8.89,
			"weather": [
				{
					"id": 804,
					"main": "Clouds",
					"description": "overcast clouds",
					"icon": "04d"
				}
			],
			"pop": 0.54
		},
		{
			"dt": 1620637200,
			"temp": 287.51,
			"feels_like": 287.46,
			"pressure": 1008,
			"humidity": 94,
			"dew_point": 285.99,
			"uvi": 0.51,
			"clouds": 100,
			"visibility": 10000,
			"wind_speed": 2.19,
			"wind_deg": 206,
			"wind_gust": 11.01,
			"weather": [
				{
					"id": 500,
					"main": "Rain",
					"description": "light rain",
					"icon": "10d"
				}
			],
			"pop": 0.58,
			"rain": {
				"1h": 0.19
			}
		},
		{
			"dt": 1620640800,
			"temp": 288.19,
			"feels_like": 288.1,
			"pressure": 1009,
			"humidity": 90,
			"dew_point": 286.09,
			"uvi": 4.45,
			"clouds": 100,
			"visibility": 10000,
			"wind_speed": 3.41,
			"wind_deg": 211,
			"wind_gust": 10.74,
			"weather": [
				{
					"id": 804,
					"main": "Clouds",
					"description": "overcast clouds",
					"icon": "04d"
				}
			],
			"pop": 0.54
		},
		{
			"dt": 1620644400,
			"temp": 288.07,
			"feels_like": 287.99,
			"pressure": 1009,
			"humidity": 91,
			"dew_point": 286.07,
			"uvi": 5.03,
			"clouds": 100,
			"visibility": 10000,
			"wind_speed": 3.19,
			"wind_deg": 227,
			"wind_gust": 9.3,
			"weather": [
				{
					"id": 804,
					"main": "Clouds",
					"description": "overcast clouds",
					"icon": "04d"
				}
			],
			"pop": 0.46
		},
		{
			"dt": 1620648000,
			"temp": 289.55,
			"feels_like": 289.36,
			"pressure": 1009,
			"humidity": 81,
			"dew_point": 285.73,
			"uvi": 5.01,
			"clouds": 100,
			"visibility": 10000,
			"wind_speed": 3.24,
			"wind_deg": 227,
			"wind_gust": 7.62,
			"weather": [
				{
					"id": 804,
					"main": "Clouds",
					"description": "overcast clouds",
					"icon": "04d"
				}
			],
			"pop": 0.42
		},
		{
			"dt": 1620651600,
			"temp": 289.55,
			"feels_like": 289.33,
			"pressure": 1009,
			"humidity": 80,
			"dew_point": 285.45,
			"uvi": 2.14,
			"clouds": 100,
			"visibility": 10000,
			"wind_speed": 2.71,
			"wind_deg": 215,
			"wind_gust": 5.32,
			"weather": [
				{
					"id": 500,
					"main": "Rain",
					"description": "light rain",
					"icon": "10d"
				}
			],
			"pop": 0.46,
			"rain": {
				"1h": 0.26
			}
		},
		{
			"dt": 1620655200,
			"temp": 290,
			"feels_like": 289.67,
			"pressure": 1010,
			"humidity": 74,
			"dew_point": 284.77,
			"uvi": 1.64,
			"clouds": 100,
			"visibility": 10000,
			"wind_speed": 3.79,
			"wind_deg": 218,
			"wind_gust": 6.77,
			"weather": [
				{
					"id": 804,
					"main": "Clouds",
					"description": "overcast clouds",
					"icon": "04d"
				}
			],
			"pop": 0.34
		},
		{
			"dt": 1620658800,
			"temp": 289.53,
			"feels_like": 289.16,
			"pressure": 1010,
			"humidity": 74,
			"dew_point": 284.36,
			"uvi": 1.08,
			"clouds": 100,
			"visibility": 10000,
			"wind_speed": 2.8,
			"wind_deg": 204,
			"wind_gust": 4.23,
			"weather": [
				{
					"id": 804,
					"main": "Clouds",
					"description": "overcast clouds",
					"icon": "04d"
				}
			],
			"pop": 0.34
		},
		{
			"dt": 1620662400,
			"temp": 287.92,
			"feels_like": 287.72,
			"pressure": 1010,
			"humidity": 87,
			"dew_point": 285.27,
			"uvi": 0.6,
			"clouds": 100,
			"visibility": 10000,
			"wind_speed": 1.97,
			"wind_deg": 200,
			"wind_gust": 3.95,
			"weather": [
				{
					"id": 500,
					"main": "Rain",
					"description": "light rain",
					"icon": "10d"
				}
			],
			"pop": 0.5,
			"rain": {
				"1h": 0.35
			}
		},
		{
			"dt": 1620666000,
			"temp": 286.47,
			"feels_like": 286.34,
			"pressure": 1010,
			"humidity": 95,
			"dew_point": 285.09,
			"uvi": 0.25,
			"clouds": 100,
			"visibility": 10000,
			"wind_speed": 1.21,
			"wind_deg": 199,
			"wind_gust": 2.26,
			"weather": [
				{
					"id": 500,
					"main": "Rain",
					"description": "light rain",
					"icon": "10d"
				}
			],
			"pop": 0.59,
			"rain": {
				"1h": 0.58
			}
		},
		{
			"dt": 1620669600,
			"temp": 285.83,
			"feels_like": 285.66,
			"pressure": 1011,
			"humidity": 96,
			"dew_point": 284.67,
			"uvi": 0.07,
			"clouds": 100,
			"visibility": 7020,
			"wind_speed": 1.67,
			"wind_deg": 183,
			"wind_gust": 2.8,
			"weather": [
				{
					"id": 501,
					"main": "Rain",
					"description": "moderate rain",
					"icon": "10d"
				}
			],
			"pop": 0.73,
			"rain": {
				"1h": 1.07
			}
		},
		{
			"dt": 1620673200,
			"temp": 285.34,
			"feels_like": 285.15,
			"pressure": 1010,
			"humidity": 97,
			"dew_point": 284.28,
			"uvi": 0,
			"clouds": 100,
			"visibility": 10000,
			"wind_speed": 0.43,
			"wind_deg": 304,
			"wind_gust": 0.9,
			"weather": [
				{
					"id": 501,
					"main": "Rain",
					"description": "moderate rain",
					"icon": "10n"
				}
			],
			"pop": 1,
			"rain": {
				"1h": 2.03
			}
		},
		{
			"dt": 1620676800,
			"temp": 285.12,
			"feels_like": 284.93,
			"pressure": 1011,
			"humidity": 98,
			"dew_point": 284.16,
			"uvi": 0,
			"clouds": 100,
			"visibility": 10000,
			"wind_speed": 0.89,
			"wind_deg": 299,
			"wind_gust": 1.16,
			"weather": [
				{
					"id": 501,
					"main": "Rain",
					"description": "moderate rain",
					"icon": "10n"
				}
			],
			"pop": 1,
			"rain": {
				"1h": 1.09
			}
		},
		{
			"dt": 1620680400,
			"temp": 285.05,
			"feels_like": 284.85,
			"pressure": 1010,
			"humidity": 98,
			"dew_point": 284.18,
			"uvi": 0,
			"clouds": 100,
			"visibility": 9686,
			"wind_speed": 0.91,
			"wind_deg": 165,
			"wind_gust": 0.97,
			"weather": [
				{
					"id": 500,
					"main": "Rain",
					"description": "light rain",
					"icon": "10n"
				}
			],
			"pop": 1,
			"rain": {
				"1h": 0.81
			}
		},
		{
			"dt": 1620684000,
			"temp": 284.9,
			"feels_like": 284.72,
			"pressure": 1010,
			"humidity": 99,
			"dew_point": 284.1,
			"uvi": 0,
			"clouds": 100,
			"visibility": 8743,
			"wind_speed": 0.14,
			"wind_deg": 152,
			"wind_gust": 1.22,
			"weather": [
				{
					"id": 501,
					"main": "Rain",
					"description": "moderate rain",
					"icon": "10n"
				}
			],
			"pop": 1,
			"rain": {
				"1h": 1.12
			}
		},
		{
			"dt": 1620687600,
			"temp": 284.9,
			"feels_like": 284.72,
			"pressure": 1010,
			"humidity": 99,
			"dew_point": 284.1,
			"uvi": 0,
			"clouds": 100,
			"visibility": 6532,
			"wind_speed": 0.99,
			"wind_deg": 226,
			"wind_gust": 1.77,
			"weather": [
				{
					"id": 501,
					"main": "Rain",
					"description": "moderate rain",
					"icon": "10n"
				}
			],
			"pop": 1,
			"rain": {
				"1h": 3.25
			}
		},
		{
			"dt": 1620691200,
			"temp": 284.84,
			"feels_like": 284.65,
			"pressure": 1010,
			"humidity": 99,
			"dew_point": 284.03,
			"uvi": 0,
			"clouds": 100,
			"visibility": 10000,
			"wind_speed": 0.88,
			"wind_deg": 249,
			"wind_gust": 1.28,
			"weather": [
				{
					"id": 501,
					"main": "Rain",
					"description": "moderate rain",
					"icon": "10n"
				}
			],
			"pop": 1,
			"rain": {
				"1h": 2.1
			}
		},
		{
			"dt": 1620694800,
			"temp": 284.75,
			"feels_like": 284.52,
			"pressure": 1009,
			"humidity": 98,
			"dew_point": 283.92,
			"uvi": 0,
			"clouds": 100,
			"visibility": 10000,
			"wind_speed": 1.15,
			"wind_deg": 277,
			"wind_gust": 2.28,
			"weather": [
				{
					"id": 500,
					"main": "Rain",
					"description": "light rain",
					"icon": "10n"
				}
			],
			"pop": 0.89,
			"rain": {
				"1h": 0.5
			}
		},
		{
			"dt": 1620698400,
			"temp": 284.9,
			"feels_like": 284.69,
			"pressure": 1008,
			"humidity": 98,
			"dew_point": 284.07,
			"uvi": 0,
			"clouds": 100,
			"visibility": 10000,
			"wind_speed": 1.28,
			"wind_deg": 274,
			"wind_gust": 3.79,
			"weather": [
				{
					"id": 500,
					"main": "Rain",
					"description": "light rain",
					"icon": "10n"
				}
			],
			"pop": 0.92,
			"rain": {
				"1h": 0.76
			}
		},
		{
			"dt": 1620702000,
			"temp": 284.98,
			"feels_like": 284.78,
			"pressure": 1009,
			"humidity": 98,
			"dew_point": 284.12,
			"uvi": 0,
			"clouds": 100,
			"visibility": 6157,
			"wind_speed": 1.95,
			"wind_deg": 242,
			"wind_gust": 3.74,
			"weather": [
				{
					"id": 500,
					"main": "Rain",
					"description": "light rain",
					"icon": "10n"
				}
			],
			"pop": 0.97,
			"rain": {
				"1h": 0.88
			}
		},
		{
			"dt": 1620705600,
			"temp": 284.95,
			"feels_like": 284.74,
			"pressure": 1009,
			"humidity": 98,
			"dew_point": 284,
			"uvi": 0,
			"clouds": 100,
			"visibility": 10000,
			"wind_speed": 1.2,
			"wind_deg": 289,
			"wind_gust": 4.04,
			"weather": [
				{
					"id": 501,
					"main": "Rain",
					"description": "moderate rain",
					"icon": "10d"
				}
			],
			"pop": 1,
			"rain": {
				"1h": 1.44
			}
		},
		{
			"dt": 1620709200,
			"temp": 285,
			"feels_like": 284.8,
			"pressure": 1009,
			"humidity": 98,
			"dew_point": 284.12,
			"uvi": 0.02,
			"clouds": 100,
			"visibility": 10000,
			"wind_speed": 1.3,
			"wind_deg": 293,
			"wind_gust": 3.56,
			"weather": [
				{
					"id": 500,
					"main": "Rain",
					"description": "light rain",
					"icon": "10d"
				}
			],
			"pop": 1,
			"rain": {
				"1h": 0.65
			}
		},
		{
			"dt": 1620712800,
			"temp": 285.3,
			"feels_like": 285.1,
			"pressure": 1008,
			"humidity": 97,
			"dew_point": 284.22,
			"uvi": 0.05,
			"clouds": 100,
			"visibility": 10000,
			"wind_speed": 1.63,
			"wind_deg": 284,
			"wind_gust": 4.51,
			"weather": [
				{
					"id": 500,
					"main": "Rain",
					"description": "light rain",
					"icon": "10d"
				}
			],
			"pop": 1,
			"rain": {
				"1h": 0.29
			}
		},
		{
			"dt": 1620716400,
			"temp": 285.89,
			"feels_like": 285.67,
			"pressure": 1009,
			"humidity": 94,
			"dew_point": 284.42,
			"uvi": 0.19,
			"clouds": 100,
			"visibility": 10000,
			"wind_speed": 1.64,
			"wind_deg": 277,
			"wind_gust": 3.33,
			"weather": [
				{
					"id": 500,
					"main": "Rain",
					"description": "light rain",
					"icon": "10d"
				}
			],
			"pop": 0.37,
			"rain": {
				"1h": 0.14
			}
		},
		{
			"dt": 1620720000,
			"temp": 285.77,
			"feels_like": 285.57,
			"pressure": 1008,
			"humidity": 95,
			"dew_point": 284.44,
			"uvi": 0.33,
			"clouds": 100,
			"visibility": 10000,
			"wind_speed": 1.5,
			"wind_deg": 314,
			"wind_gust": 3.17,
			"weather": [
				{
					"id": 500,
					"main": "Rain",
					"description": "light rain",
					"icon": "10d"
				}
			],
			"pop": 0.35,
			"rain": {
				"1h": 0.14
			}
		},
		{
			"dt": 1620723600,
			"temp": 286.46,
			"feels_like": 286.25,
			"pressure": 1008,
			"humidity": 92,
			"dew_point": 284.63,
			"uvi": 0.5,
			"clouds": 100,
			"visibility": 10000,
			"wind_speed": 1.87,
			"wind_deg": 34,
			"wind_gust": 5.4,
			"weather": [
				{
					"id": 804,
					"main": "Clouds",
					"description": "overcast clouds",
					"icon": "04d"
				}
			],
			"pop": 0.35
		},
		{
			"dt": 1620727200,
			"temp": 286.3,
			"feels_like": 286.07,
			"pressure": 1008,
			"humidity": 92,
			"dew_point": 284.47,
			"uvi": 0.8,
			"clouds": 100,
			"visibility": 10000,
			"wind_speed": 1.57,
			"wind_deg": 41,
			"wind_gust": 4.81,
			"weather": [
				{
					"id": 804,
					"main": "Clouds",
					"description": "overcast clouds",
					"icon": "04d"
				}
			],
			"pop": 0.27
		},
		{
			"dt": 1620730800,
			"temp": 286.08,
			"feels_like": 285.83,
			"pressure": 1008,
			"humidity": 92,
			"dew_point": 284.32,
			"uvi": 0.9,
			"clouds": 100,
			"visibility": 10000,
			"wind_speed": 1.28,
			"wind_deg": 46,
			"wind_gust": 3.42,
			"weather": [
				{
					"id": 500,
					"main": "Rain",
					"description": "light rain",
					"icon": "10d"
				}
			],
			"pop": 0.4,
			"rain": {
				"1h": 0.15
			}
		},
		{
			"dt": 1620734400,
			"temp": 285.84,
			"feels_like": 285.62,
			"pressure": 1009,
			"humidity": 94,
			"dew_point": 284.32,
			"uvi": 0.89,
			"clouds": 100,
			"visibility": 10000,
			"wind_speed": 0.56,
			"wind_deg": 66,
			"wind_gust": 2.08,
			"weather": [
				{
					"id": 500,
					"main": "Rain",
					"description": "light rain",
					"icon": "10d"
				}
			],
			"pop": 0.54,
			"rain": {
				"1h": 0.27
			}
		},
		{
			"dt": 1620738000,
			"temp": 285.58,
			"feels_like": 285.39,
			"pressure": 1009,
			"humidity": 96,
			"dew_point": 284.32,
			"uvi": 0.42,
			"clouds": 100,
			"visibility": 10000,
			"wind_speed": 0.66,
			"wind_deg": 356,
			"wind_gust": 2.17,
			"weather": [
				{
					"id": 500,
					"main": "Rain",
					"description": "light rain",
					"icon": "10d"
				}
			],
			"pop": 0.7,
			"rain": {
				"1h": 0.37
			}
		},
		{
			"dt": 1620741600,
			"temp": 285.49,
			"feels_like": 285.29,
			"pressure": 1009,
			"humidity": 96,
			"dew_point": 284.29,
			"uvi": 0.32,
			"clouds": 100,
			"visibility": 10000,
			"wind_speed": 0.69,
			"wind_deg": 333,
			"wind_gust": 1.83,
			"weather": [
				{
					"id": 500,
					"main": "Rain",
					"description": "light rain",
					"icon": "10d"
				}
			],
			"pop": 0.72,
			"rain": {
				"1h": 0.27
			}
		},
		{
			"dt": 1620745200,
			"temp": 285.3,
			"feels_like": 285.08,
			"pressure": 1008,
			"humidity": 96,
			"dew_point": 284.09,
			"uvi": 0.21,
			"clouds": 100,
			"visibility": 10000,
			"wind_speed": 1.44,
			"wind_deg": 26,
			"wind_gust": 4.43,
			"weather": [
				{
					"id": 804,
					"main": "Clouds",
					"description": "overcast clouds",
					"icon": "04d"
				}
			],
			"pop": 0.71
		},
		{
			"dt": 1620748800,
			"temp": 286.61,
			"feels_like": 286.28,
			"pressure": 1008,
			"humidity": 87,
			"dew_point": 283.96,
			"uvi": 0.49,
			"clouds": 100,
			"visibility": 10000,
			"wind_speed": 0.98,
			"wind_deg": 23,
			"wind_gust": 2.28,
			"weather": [
				{
					"id": 804,
					"main": "Clouds",
					"description": "overcast clouds",
					"icon": "04d"
				}
			],
			"pop": 0.69
		},
		{
			"dt": 1620752400,
			"temp": 286.4,
			"feels_like": 286.1,
			"pressure": 1008,
			"humidity": 89,
			"dew_point": 284.06,
			"uvi": 0.21,
			"clouds": 100,
			"visibility": 10000,
			"wind_speed": 0.96,
			"wind_deg": 44,
			"wind_gust": 1.85,
			"weather": [
				{
					"id": 804,
					"main": "Clouds",
					"description": "overcast clouds",
					"icon": "04d"
				}
			],
			"pop": 0.69
		},
		{
			"dt": 1620756000,
			"temp": 285.73,
			"feels_like": 285.45,
			"pressure": 1008,
			"humidity": 92,
			"dew_point": 283.98,
			"uvi": 0.06,
			"clouds": 100,
			"visibility": 10000,
			"wind_speed": 0.73,
			"wind_deg": 7,
			"wind_gust": 0.88,
			"weather": [
				{
					"id": 804,
					"main": "Clouds",
					"description": "overcast clouds",
					"icon": "04d"
				}
			],
			"pop": 0.61
		},
		{
			"dt": 1620759600,
			"temp": 284.5,
			"feels_like": 284.17,
			"pressure": 1009,
			"humidity": 95,
			"dew_point": 283.12,
			"uvi": 0,
			"clouds": 100,
			"visibility": 10000,
			"wind_speed": 0.06,
			"wind_deg": 265,
			"wind_gust": 0.39,
			"weather": [
				{
					"id": 804,
					"main": "Clouds",
					"description": "overcast clouds",
					"icon": "04d"
				}
			],
			"pop": 0.07
		},
		{
			"dt": 1620763200,
			"temp": 284.59,
			"feels_like": 284.27,
			"pressure": 1009,
			"humidity": 95,
			"dew_point": 283.18,
			"uvi": 0,
			"clouds": 100,
			"visibility": 10000,
			"wind_speed": 0.09,
			"wind_deg": 319,
			"wind_gust": 0.35,
			"weather": [
				{
					"id": 804,
					"main": "Clouds",
					"description": "overcast clouds",
					"icon": "04n"
				}
			],
			"pop": 0.04
		},
		{
			"dt": 1620766800,
			"temp": 284.38,
			"feels_like": 284.04,
			"pressure": 1009,
			"humidity": 95,
			"dew_point": 283.09,
			"uvi": 0,
			"clouds": 100,
			"visibility": 10000,
			"wind_speed": 0.79,
			"wind_deg": 279,
			"wind_gust": 0.75,
			"weather": [
				{
					"id": 804,
					"main": "Clouds",
					"description": "overcast clouds",
					"icon": "04n"
				}
			],
			"pop": 0
		},
		{
			"dt": 1620770400,
			"temp": 284.37,
			"feels_like": 284.05,
			"pressure": 1008,
			"humidity": 96,
			"dew_point": 283.17,
			"uvi": 0,
			"clouds": 100,
			"visibility": 10000,
			"wind_speed": 1.33,
			"wind_deg": 277,
			"wind_gust": 1.62,
			"weather": [
				{
					"id": 804,
					"main": "Clouds",
					"description": "overcast clouds",
					"icon": "04n"
				}
			],
			"pop": 0
		}
	],
	"daily": [
		{
			"dt": 1620644400,
			"sunrise": 1620618337,
			"sunset": 1620673188,
			"moonrise": 1620617640,
			"moonset": 1620668340,
			"moon_phase": 0.96,
			"temp": {
				"day": 288.07,
				"min": 285.05,
				"max": 290,
				"night": 285.05,
				"eve": 286.47,
				"morn": 287.06
			},
			"feels_like": {
				"day": 287.99,
				"night": 286.96,
				"eve": 286.34,
				"morn": 286.96
			},
			"pressure": 1009,
			"humidity": 91,
			"dew_point": 286.07,
			"wind_speed": 3.79,
			"wind_deg": 218,
			"wind_gust": 11.01,
			"weather": [
				{
					"id": 501,
					"main": "Rain",
					"description": "moderate rain",
					"icon": "10d"
				}
			],
			"clouds": 100,
			"pop": 1,
			"rain": 8.25,
			"uvi": 5.03
		},
		{
			"dt": 1620730800,
			"sunrise": 1620704645,
			"sunset": 1620759679,
			"moonrise": 1620705000,
			"moonset": 1620758820,
			"moon_phase": 0,
			"temp": {
				"day": 286.08,
				"min": 284.38,
				"max": 286.61,
				"night": 284.38,
				"eve": 286.4,
				"morn": 285
			},
			"feels_like": {
				"day": 285.83,
				"night": 284.8,
				"eve": 286.1,
				"morn": 284.8
			},
			"pressure": 1008,
			"humidity": 92,
			"dew_point": 284.32,
			"wind_speed": 1.95,
			"wind_deg": 242,
			"wind_gust": 5.4,
			"weather": [
				{
					"id": 501,
					"main": "Rain",
					"description": "moderate rain",
					"icon": "10d"
				}
			],
			"clouds": 100,
			"pop": 1,
			"rain": 12.33,
			"uvi": 0.9
		},
		{
			"dt": 1620817200,
			"sunrise": 1620790954,
			"sunset": 1620846169,
			"moonrise": 1620792540,
			"moonset": 1620849300,
			"moon_phase": 0.02,
			"temp": {
				"day": 284.66,
				"min": 283.18,
				"max": 285.13,
				"night": 283.18,
				"eve": 284.2,
				"morn": 284.05
			},
			"feels_like": {
				"day": 284.32,
				"night": 283.73,
				"eve": 283.76,
				"morn": 283.73
			},
			"pressure": 1009,
			"humidity": 94,
			"dew_point": 283.13,
			"wind_speed": 4.8,
			"wind_deg": 291,
			"wind_gust": 8.85,
			"weather": [
				{
					"id": 500,
					"main": "Rain",
					"description": "light rain",
					"icon": "10d"
				}
			],
			"clouds": 100,
			"pop": 0.81,
			"rain": 2,
			"uvi": 1.82
		},
		{
			"dt": 1620903600,
			"sunrise": 1620877264,
			"sunset": 1620932658,
			"moonrise": 1620880380,
			"moonset": 1620939720,
			"moon_phase": 0.05,
			"temp": {
				"day": 283.74,
				"min": 281.94,
				"max": 284.22,
				"night": 282.39,
				"eve": 282.64,
				"morn": 281.94
			},
			"feels_like": {
				"day": 283.26,
				"night": 280.92,
				"eve": 282.64,
				"morn": 280.92
			},
			"pressure": 1008,
			"humidity": 92,
			"dew_point": 281.84,
			"wind_speed": 3.28,
			"wind_deg": 303,
			"wind_gust": 7.5,
			"weather": [
				{
					"id": 500,
					"main": "Rain",
					"description": "light rain",
					"icon": "10d"
				}
			],
			"clouds": 100,
			"pop": 0.81,
			"rain": 3,
			"uvi": 1.83
		},
		{
			"dt": 1620990000,
			"sunrise": 1620963577,
			"sunset": 1621019147,
			"moonrise": 1620968640,
			"moonset": 0,
			"moon_phase": 0.08,
			"temp": {
				"day": 290.79,
				"min": 281.49,
				"max": 291.23,
				"night": 282.39,
				"eve": 287.13,
				"morn": 283.24
			},
			"feels_like": {
				"day": 289.68,
				"night": 282.73,
				"eve": 286.33,
				"morn": 282.73
			},
			"pressure": 1009,
			"humidity": 41,
			"dew_point": 276.98,
			"wind_speed": 2.9,
			"wind_deg": 281,
			"wind_gust": 3.76,
			"weather": [
				{
					"id": 500,
					"main": "Rain",
					"description": "light rain",
					"icon": "10d"
				}
			],
			"clouds": 100,
			"pop": 0.37,
			"rain": 0.19,
			"uvi": 5.25
		},
		{
			"dt": 1621076400,
			"sunrise": 1621049892,
			"sunset": 1621105635,
			"moonrise": 1621057380,
			"moonset": 1621029840,
			"moon_phase": 0.11,
			"temp": {
				"day": 290.66,
				"min": 279.77,
				"max": 290.66,
				"night": 282.33,
				"eve": 287.03,
				"morn": 283.92
			},
			"feels_like": {
				"day": 289.88,
				"night": 282.98,
				"eve": 286.48,
				"morn": 282.98
			},
			"pressure": 1013,
			"humidity": 54,
			"dew_point": 280.69,
			"wind_speed": 2.06,
			"wind_deg": 10,
			"wind_gust": 5,
			"weather": [
				{
					"id": 500,
					"main": "Rain",
					"description": "light rain",
					"icon": "10d"
				}
			],
			"clouds": 99,
			"pop": 0.39,
			"rain": 0.59,
			"uvi": 6
		},
		{
			"dt": 1621162800,
			"sunrise": 1621136208,
			"sunset": 1621192121,
			"moonrise": 1621146780,
			"moonset": 1621119600,
			"moon_phase": 0.14,
			"temp": {
				"day": 282.67,
				"min": 280.69,
				"max": 287.24,
				"night": 280.77,
				"eve": 285.15,
				"morn": 281.38
			},
			"feels_like": {
				"day": 282.67,
				"night": 281.38,
				"eve": 284.55,
				"morn": 281.38
			},
			"pressure": 1016,
			"humidity": 90,
			"dew_point": 280.6,
			"wind_speed": 2.15,
			"wind_deg": 69,
			"wind_gust": 5.06,
			"weather": [
				{
					"id": 501,
					"main": "Rain",
					"description": "moderate rain",
					"icon": "10d"
				}
			],
			"clouds": 100,
			"pop": 0.95,
			"rain": 6.74,
			"uvi": 6
		},
		{
			"dt": 1621249200,
			"sunrise": 1621222527,
			"sunset": 1621278607,
			"moonrise": 1621236780,
			"moonset": 1621208820,
			"moon_phase": 0.17,
			"temp": {
				"day": 284.85,
				"min": 280.45,
				"max": 287.32,
				"night": 281.18,
				"eve": 285.22,
				"morn": 281.86
			},
			"feels_like": {
				"day": 284.5,
				"night": 281.86,
				"eve": 284.75,
				"morn": 281.86
			},
			"pressure": 1011,
			"humidity": 93,
			"dew_point": 283.09,
			"wind_speed": 4.11,
			"wind_deg": 244,
			"wind_gust": 7.75,
			"weather": [
				{
					"id": 500,
					"main": "Rain",
					"description": "light rain",
					"icon": "10d"
				}
			],
			"clouds": 100,
			"pop": 1,
			"rain": 7.89,
			"uvi": 6
		}
	],
	"alerts": [
		{
			"sender_name": "Deutscher Wetterdienst",
			"event": "WINDBÖEN",
			"start": 1620619200,
			"end": 1620673200,
			"description": "Es treten oberhalb 400 m Windböen mit Geschwindigkeiten bis 60 km/h (17m/s, 33kn, Bft 7) aus südwestlicher Richtung auf. In exponierten Lagen muss mit Sturmböen bis 70 km/h (20m/s, 38kn, Bft 8) gerechnet werden."
		},
		{
			"sender_name": "Deutscher Wetterdienst",
			"event": "wind gusts",
			"start": 1620612000,
			"end": 1620662400,
			"description": "There is a risk of wind gusts (level 1 of 4).\nMax. gusts: \u003c 60 km/h; Wind direction: south-west; Increased gusts: in exposed locations \u003c 70 km/h"
		}
	]
}
