{
	"deviceMapping": {
		"id": [
			"chuangmi.plug.v3"
		],
		"channels": [
			{
				"property": "power",
				"friendlyName": "Power",
				"channel": "power",
				"type": "Switch",
				"refresh": true,
				"channelGroup": "actions",
				"actions": [
					{
						"command": "set_*",
						"parameterType": "ONOFFPARA"
					}
				]
			},
			{
				"property": "usb_on",
				"friendlyName": "USB",
				"channel": "usb",
				"type": "Switch",
				"refresh": true,
				"ChannelGroup": "actions",
				"actions": [
					{
						"command": "set_usb_*",
						"parameterType": "ONOFFPARA"
					}
				]
			},
			{
				"property": "temperature",
				"friendlyName": "Temperature",
				"channel": "temperature",
				"type": "Number",
				"refresh": true,
				"ChannelGroup": "",
				"actions": []
			},
			{
				"property": "wifi_led",
				"friendlyName": "Wifi led",
				"channel": "led",
				"type": "Switch",
				"refresh": true,
				"ChannelGroup": "actions",
				"actions": [
					{
						"command": "set_wifi_led",
						"parameterType": "ONOFF"
					}
				]
			}
		]
	}
}

