<?xml version="1.0" encoding="UTF-8"?>
<thing:thing-descriptions bindingId="zwave"
  xmlns:xsi="http://www.w3.org/2001/XMLSchema-instance"
  xmlns:thing="http://eclipse.org/smarthome/schemas/thing-description/v1.0.0"
  xsi:schemaLocation="http://eclipse.org/smarthome/schemas/thing-description/v1.0.0
                      http://eclipse.org/smarthome/schemas/thing-description/v1.0.0">

  <thing-type id="everspring_ad131_00_000" listed="false">
    <label>AD131 Dimmer Plugin</label>
    <description>Dimmer Plugin</description>

    <!-- CHANNEL DEFINITIONS -->
    <channels>
      <channel id="switch_dimmer" typeId="switch_dimmer">
        <label>Dimmer</label>
        <properties>
          <property name="binding:*:PercentType">SWITCH_MULTILEVEL,BASIC</property>
          <property name="binding:Command:OnOffType">SWITCH_MULTILEVEL,BASIC</property>
        </properties>
      </channel>
    </channels>

    <!-- DEVICE PROPERTY DEFINITIONS -->
    <properties>
      <property name="vendor">Everspring</property>
      <property name="modelId">AD131</property>
      <property name="manufacturerId">0060</property>
      <property name="manufacturerRef">0003:0001</property>
    </properties>

  </thing-type>
</thing:thing-descriptions>
