<?xml version="1.0" encoding="UTF-8"?>
<thing:thing-descriptions bindingId="zwave"
  xmlns:xsi="http://www.w3.org/2001/XMLSchema-instance"
  xmlns:thing="http://eclipse.org/smarthome/schemas/thing-description/v1.0.0"
  xsi:schemaLocation="http://eclipse.org/smarthome/schemas/thing-description/v1.0.0
                      http://eclipse.org/smarthome/schemas/thing-description/v1.0.0">

  <thing-type id="fibaro_fgrm222_00_000" listed="false">
    <label>FGRM222 Roller Shutter</label>
    <description>Roller Shutter</description>

    <!-- CHANNEL DEFINITIONS -->
    <channels>
      <channel id="switch_binary" typeId="switch_binary">
        <label>Switch</label>
        <properties>
          <property name="binding:*:OnOffType">SWITCH_BINARY</property>
        </properties>
      </channel>
      <channel id="blinds_control" typeId="blinds_control">
        <label>Blinds control</label>
        <properties>
          <property name="binding:*:PercentType">SWITCH_MULTILEVEL</property>
          <property name="binding:Command:StopMoveType">SWITCH_MULTILEVEL</property>
          <property name="binding:Command:UpDownType">SWITCH_MULTILEVEL</property>
        </properties>
      </channel>
      <channel id="sensor_power" typeId="sensor_power">
        <label>Sensor (power)</label>
        <properties>
          <property name="binding:*:DecimalType">SENSOR_MULTILEVEL;type=POWER</property>
        </properties>
      </channel>
      <channel id="meter_watts" typeId="meter_watts">
        <label>Meter (watts)</label>
        <properties>
          <property name="binding:*:DecimalType">METER;type=E_W</property>
        </properties>
      </channel>
      <channel id="meter_kwh" typeId="meter_kwh">
        <label>Meter (kWh)</label>
        <properties>
          <property name="binding:*:DecimalType">METER;type=E_KWH</property>
        </properties>
      </channel>
    </channels>

    <!-- DEVICE PROPERTY DEFINITIONS -->
    <properties>
      <property name="vendor">Fibaro System</property>
      <property name="modelId">FGRM222</property>
      <property name="manufacturerId">010F</property>
      <property name="manufacturerRef">0301:1001,0302:1000</property>
      <property name="defaultAssociations">3</property>
    </properties>

    <!-- CONFIGURATION DESCRIPTIONS -->
    <config-description>

      <!-- PARAMETER DEFINITIONS -->
      <parameter-group name="configuration">
        <context>setup</context>
        <label>Configuration Parameters</label>
      </parameter-group>

      <parameter name="config_1_1" type="integer" groupName="configuration">
        <label>1: Local protection</label>
        <description>Enables/disables local entry. If activated module stops responding to S1 and S2 push buttons, SCENE ID and association commands will not be sent. Only exception is the B-button.</description>
        <default>255</default>
        <options>
          <option value="0">No protection. Roller Shutter responds to push buttons</option>
          <option value="2">Local protection active. Roller Shutter does not respond to push butto</option>
        </options>
      </parameter>

      <parameter name="config_2_1" type="integer" groupName="configuration">
        <label>2: Radio protection</label>
        <description>Enables/disables RF protection. If activated device stops responding to command frames. Configuration and polling still possible.</description>
        <default>0</default>
        <options>
          <option value="0">No protection. Roller Shutter responds to command frames.</option>
          <option value="1">RF Protection active. Roller Shutter does not respond to the Z-Wave co</option>
        </options>
      </parameter>

      <parameter name="config_3_1" type="integer" groupName="configuration">
        <label>3: Reports type</label>
        <description>Parameters value shoud be set to 1 if the module operates in Venetian Blind mode.</description>
        <default>0</default>
        <options>
          <option value="0">Blind position reports sent to the main controller using Z-Wave Comman</option>
          <option value="1">Blind position reports sent to the main controller using Fibar Command</option>
        </options>
      </parameter>

      <parameter name="config_10_1" type="integer" groupName="configuration">
        <label>10: Roller Shutter operating modes</label>
        <default>1</default>
        <options>
          <option value="0">Roller Blind Mode, without positioning</option>
          <option value="1">Roller Blind Mode, with positioning</option>
          <option value="2">Venetian Blind Mode, with positioning</option>
          <option value="3">Gate Mode, without positioning</option>
          <option value="4">Gate Mode, with positioning</option>
        </options>
      </parameter>

      <parameter name="config_12_2" type="integer" groupName="configuration"
                 min="0" max="65535">
        <label>12: Turning time/ delay time</label>
        <description>In Venetian Blind mode (parameter 10 set to 2) the parameter determines time of full turn of the lamellas. In Gate Mode (parameter 10 set to 3 or 4) the parameter defines the delay time after which an open gate starts closing. Type range</description>
        <default>150</default>
      </parameter>

      <parameter name="config_13_1" type="integer" groupName="configuration">
        <label>13: Lamellas positioning mode</label>
        <description>Parameter influences the lamellas positioning in venetian blind mode (parameter 10 set to 2)</description>
        <default>1</default>
        <options>
          <option value="0">Lamellas return to previously set position only in case of the main co</option>
          <option value="1">Lamellas return to previously set position in case of the main control</option>
          <option value="2">Lamellas return to previously set position in case of the main control</option>
        </options>
      </parameter>

      <parameter name="config_14_1" type="integer" groupName="configuration">
        <label>14: Switch type</label>
        <description>parameter settings are relevant for Roller Blind Mode and Venetian Blind Mode (parameter 10 set to 0, 1, 2).</description>
        <default>0</default>
        <options>
          <option value="0">Momentary switches</option>
          <option value="1">Toggle switches</option>
          <option value="2">Single, momentary switch.</option>
        </options>
      </parameter>

      <parameter name="config_17_1" type="integer" groupName="configuration"
                 min="0" max="255">
        <label>17: Delay time after S2</label>
        <description>In roller blind mode or venetian blind mode (parameter 10 set to 0, 1, 2) the parameter determines when the Roller Shutter relays are turned off after reaching a limit switch. In Gate Mode (parameter 10 set to 3 or 4) the parameter determines a time perio</description>
        <default>10</default>
      </parameter>

      <parameter name="config_18_1" type="integer" groupName="configuration"
                 min="0" max="255">
        <label>18: Motor operation detection</label>
        <description>Power threshold to be interpreted as reaching a limit switch.</description>
        <default>10</default>
      </parameter>

      <parameter name="config_22_2" type="integer" groupName="configuration"
                 min="0" max="65535">
        <label>22: Motor operation time</label>
        <description>Time period for the motor to continue operation.</description>
        <default>10</default>
      </parameter>

      <parameter name="config_29_1" type="integer" groupName="configuration">
        <label>29: Forced Roller Shutter calibration</label>
        <description>Seting the parameter to 1 Roller Shutter enters the calibration mode. Parameter is only only relevant if a Roller Shutter is set to work in positioning mode (parameter 10 set to 1, 2 or 4).</description>
        <default>0</default>
        <options>
          <option value="0">Deactivated</option>
          <option value="1">Start calibration process</option>
        </options>
      </parameter>

      <parameter name="config_30_1" type="integer" groupName="configuration">
        <label>30: Response to General Alarm</label>
        <default>2</default>
        <options>
          <option value="0">No response to alarm frames</option>
          <option value="1">Open Blind</option>
          <option value="2">Close Blind</option>
        </options>
      </parameter>

      <parameter name="config_31_1" type="integer" groupName="configuration">
        <label>31: Response to Water Flood Alarm</label>
        <default>0</default>
        <options>
          <option value="0">No response to alarm frames</option>
          <option value="1">Open Blind</option>
          <option value="2">Close Blind</option>
        </options>
      </parameter>

      <parameter name="config_32_1" type="integer" groupName="configuration">
        <label>32: Response to Smoke, CO, CO2 Alarm</label>
        <default>3</default>
        <options>
          <option value="0">No response to alarm frames</option>
          <option value="1">Open Blind</option>
          <option value="2">Close Blind</option>
        </options>
      </parameter>

      <parameter name="config_33_1" type="integer" groupName="configuration">
        <label>33: Response to Temperature Alarm</label>
        <default>1</default>
        <options>
          <option value="0">No response to alarm frames</option>
          <option value="1">Open Blind</option>
          <option value="2">Close Blind</option>
        </options>
      </parameter>

      <parameter name="config_35_1" type="integer" groupName="configuration">
        <label>35: Managing lamellas in response to alarm</label>
        <description>In Venetian Blind Mode (parameter 10 set to 2), the parameter determines how the lamellas will react upon alarm detection.</description>
        <default>1</default>
        <options>
          <option value="0">Do not change lamellas position</option>
          <option value="1">Set lamellas to their extreme position</option>
        </options>
      </parameter>

      <parameter name="config_40_1" type="integer" groupName="configuration"
                 min="0" max="100">
        <label>40: Power reports</label>
        <description>Power level change that will result in new power value report being sent. value is a percentage of the previous report.</description>
        <default>10</default>
      </parameter>

      <parameter name="config_42_2" type="integer" groupName="configuration"
                 min="-32767" max="32767">
        <label>42: Periodic power or energy reports</label>
        <description>Time to the next report. Value of 0 means the reports are turned off.</description>
        <default>3600</default>
      </parameter>

      <parameter name="config_43_1" type="integer" groupName="configuration"
                 min="-126" max="127">
        <label>43: Energy reports</label>
        <description>Energy level change which will result in new energy value report being sent. Value of 0 means the reports are turned off.</description>
        <default>10</default>
      </parameter>

      <parameter name="config_44_1" type="integer" groupName="configuration">
        <label>44: Self-measurement</label>
        <description>Enables/disables to include the power and energy used by itself in reports to main controller.</description>
        <default>0</default>
        <options>
          <option value="0">Disabled</option>
          <option value="1">Activated</option>
        </options>
      </parameter>

      <parameter name="config_50_1" type="integer" groupName="configuration">
        <label>50: Scenes/ Associations activation</label>
        <description>Parameter determines whether scenes or associations are activated by the switch keys.</description>
        <default>0</default>
        <options>
          <option value="0">Associations Active</option>
          <option value="1">Scenes Active</option>
        </options>
      </parameter>

      <!-- ASSOCIATION DEFINITIONS -->
      <parameter-group name="association">
        <context>link</context>
        <label>Association Groups</label>
      </parameter-group>

      <parameter name="group_1" type="text" groupName="association" multiple="true">
        <label>1: Momentary click</label>
        <multipleLimit>16</multipleLimit>
      </parameter>

      <parameter name="group_2" type="text" groupName="association" multiple="true">
        <label>2: Momentary hold</label>
        <multipleLimit>16</multipleLimit>
      </parameter>

      <parameter name="group_3" type="text" groupName="association">
        <label>3: Controller Updates</label>
      </parameter>

    </config-description>

  </thing-type>
</thing:thing-descriptions>
