{
	"deviceMapping": {
		"id": [
			"dmaker.airfresh.t2017"
		],
		"channels": [
			{
				"property": "power",
				"friendlyName": "Power",
				"channel": "power",
				"type": "Switch",
				"refresh": true,
				"actions": [
					{
						"command": "set_power",
						"parameterType": "ONOFFBOOL"
					}
				],
				"category": "switch",
				"tags": [
					"Switch"
				]
			},
			{
				"property": "mode",
				"friendlyName": "Mode",
				"channel": "airFreshMode",
				"type": "String",
				"stateDescription": {
					"options": [
						{
							"value": "auto",
							"label": "Auto"
						},
						{
							"value": "sleep",
							"label": "Sleep"
						},
						{
							"value": "favourite",
							"label": "Favorite"
						}
					]
				},
				"refresh": true,
				"actions": [
					{
						"command": "set_mode",
						"parameterType": "STRING"
					}
				],
				"tags": [
					"Control"
				],
				"readmeComment": "Value mapping `[\"auto\"\u003d\"Auto\",\"sleep\"\u003d\"Sleep\",\"favourite\"\u003d\"Favorite\"]`"
			},
			{
				"property": "ptc_on",
				"friendlyName": "PTC",
				"channel": "airFreshPTCPower",
				"type": "Switch",
				"refresh": true,
				"actions": [
					{
						"command": "set_ptc_on",
						"parameterType": "ONOFFBOOL"
					}
				]
			},
			{
				"property": "ptc_level",
				"friendlyName": "PTC Level",
				"channel": "airFreshPtcLevel",
				"type": "String",
				"stateDescription": {
					"options": [
						{
							"value": "low",
							"label": "Low"
						},
						{
							"value": "medium",
							"label": "Medium"
						},
						{
							"value": "high",
							"label": "High"
						}
					]
				},
				"refresh": true,
				"actions": [
					{
						"command": "set_ptc_level",
						"parameterType": "STRING"
					}
				],
				"readmeComment": "Value mapping `[\"low\"\u003d\"Low\",\"medium\"\u003d\"Medium\",\"high\"\u003d\"High\"]`"
			},
			{
				"property": "ptc_status",
				"friendlyName": "PTC Status",
				"channel": "airFreshPTCStatus",
				"type": "Switch",
				"refresh": true,
				"ChannelGroup": "Status",
				"actions": []
			},
			{
				"property": "screen_direction",
				"friendlyName": "Screen direction",
				"channel": "airFreshDisplayDirection",
				"type": "String",
				"stateDescription": {
					"options": [
						{
							"value": "forward",
							"label": "Normal"
						},
						{
							"value": "left",
							"label": "Left"
						},
						{
							"value": "right",
							"label": "Right"
						}
					]
				},
				"refresh": true,
				"actions": [
					{
						"command": "set_screen_direction",
						"parameterType": "STRING"
					}
				],
				"readmeComment": "Value mapping `[\"forward\"\u003d\"Normal\",\"left\"\u003d\"Left\",\"right\"\u003d\"Right\"]`"
			},
			{
				"property": "display",
				"friendlyName": "Display",
				"channel": "airFreshDisplay",
				"type": "Switch",
				"refresh": true,
				"actions": [
					{
						"command": "set_display",
						"parameterType": "ONOFFBOOL"
					}
				]
			},
			{
				"property": "child_lock",
				"friendlyName": "Child Lock",
				"channel": "airFreshChildLock",
				"type": "Switch",
				"refresh": true,
				"actions": [
					{
						"command": "set_child_lock",
						"parameterType": "ONOFFBOOL"
					}
				]
			},
			{
				"property": "sound",
				"friendlyName": "Sound",
				"channel": "airFreshSound",
				"type": "Switch",
				"refresh": true,
				"actions": [
					{
						"command": "set_sound",
						"parameterType": "ONOFFBOOL"
					}
				]
			},
			{
				"property": "pm25",
				"friendlyName": "PM2.5",
				"channel": "airFreshPM25",
				"type": "Number",
				"stateDescription": {
					"pattern": "%.0f"
				},
				"refresh": true,
				"ChannelGroup": "Status",
				"actions": []
			},
			{
				"property": "co2",
				"friendlyName": "CO2",
				"channel": "airFreshCO2",
				"type": "Number",
				"stateDescription": {
					"pattern": "%.0f"
				},
				"refresh": true,
				"ChannelGroup": "Status",
				"actions": [],
				"category": "co2",
				"tags": [
					"Measurement",
					"CO2"
				]
			},
			{
				"property": "control_speed",
				"friendlyName": "Current Speed",
				"channel": "airFreshCurrentSpeed",
				"type": "Number",
				"stateDescription": {
					"pattern": "%.0f m³/h"
				},
				"refresh": true,
				"ChannelGroup": "Status",
				"actions": []
			},
			{
				"property": "favourite_speed",
				"friendlyName": "Favorite Speed",
				"channel": "airFreshFavoriteSpeed",
				"type": "Number",
				"stateDescription": {
					"minimum": 0,
					"maximum": 300,
					"pattern": "%.0f"
				},
				"refresh": true,
				"actions": [
					{
						"command": "set_favourite_speed",
						"parameterType": "NUMBER"
					}
				]
			},
			{
				"property": "temperature_outside",
				"friendlyName": "Temperature Outside",
				"channel": "airFreshTemperature",
				"type": "Number",
				"stateDescription": {
					"pattern": "%.0f°C"
				},
				"refresh": true,
				"ChannelGroup": "Status",
				"actions": []
			},
			{
				"property": "filter_intermediate",
				"friendlyName": "Filter Percents Remaining",
				"channel": "airFreshFilterPercents",
				"type": "Number",
				"stateDescription": {
					"pattern": "%.0f%%"
				},
				"refresh": true,
				"actions": []
			},
			{
				"property": "filter_inter_day",
				"friendlyName": "Filter Days Remaining",
				"channel": "airFreshFilterDays",
				"type": "Number",
				"stateDescription": {
					"pattern": "%.0f"
				},
				"refresh": true,
				"ChannelGroup": "Status",
				"actions": []
			},
			{
				"property": "filter_efficient",
				"friendlyName": "Filter Pro Percents Remaining",
				"channel": "airFreshFilterProPercents",
				"type": "Number",
				"stateDescription": {
					"pattern": "%.0f%%"
				},
				"refresh": true,
				"ChannelGroup": "Status",
				"actions": []
			},
			{
				"property": "filter_effi_day",
				"friendlyName": "Filter Pro Days Remaining",
				"channel": "airFreshFilterProDays",
				"type": "Number",
				"stateDescription": {
					"pattern": "%.0f"
				},
				"refresh": true,
				"ChannelGroup": "Status",
				"actions": []
			},
			{
				"property": "",
				"friendlyName": "Reset Filter",
				"channel": "airFreshResetFilter",
				"type": "String",
				"refresh": false,
				"ChannelGroup": "actions",
				"actions": [
					{
						"command": "set_filter_reset",
						"parameterType": "STRING"
					}
				]
			}
		]
	}
}
