<?xml version="1.0" encoding="UTF-8"?>
<thing:thing-descriptions bindingId="upb" xmlns:xsi="http://www.w3.org/2001/XMLSchema-instance"
	xmlns:thing="https://openhab.org/schemas/thing-description/v1.0.0"
	xsi:schemaLocation="https://openhab.org/schemas/thing-description/v1.0.0 https://openhab.org/schemas/thing-description-1.0.0.xsd">

	<thing-type id="generic">
		<supported-bridge-type-refs>
			<bridge-type-ref id="serial-pim"/>
		</supported-bridge-type-refs>
		<label>Generic Powerline Device</label>
		<description>A generic device in a UPB network</description>
		<category>WallSwitch</category>
		<semantic-equipment-tag>ControlDevice</semantic-equipment-tag>
		<channels>
			<channel id="dimmer" typeId="system.brightness"/>
		</channels>

		<config-description-ref uri="thing-type:upb:device-address"/>
	</thing-type>

</thing:thing-descriptions>
