<?xml version="1.0" encoding="UTF-8"?>
<thing:thing-descriptions bindingId="sonos"
	xmlns:xsi="http://www.w3.org/2001/XMLSchema-instance"
	xmlns:thing="http://eclipse.org/smarthome/schemas/thing-description/v1.0.0"
	xsi:schemaLocation="http://eclipse.org/smarthome/schemas/thing-description/v1.0.0 http://eclipse.org/smarthome/schemas/thing-description-1.0.0.xsd">

	<!-- Player Thing Type -->
	<thing-type id="zoneplayer">
		<label>Zone Player</label>
		<description>The Zone Player represents a Sonos Zone Player like the ZP120, Connect:Amp, Play:1 etc</description>

		<channels>
			<channel id="add" typeId="add" />
			<channel id="alarm" typeId="alarm" />
			<channel id="alarmproperties" typeId="alarmproperties" />
			<channel id="alarmrunning" typeId="alarmrunning" />
			<channel id="control" typeId="control" />
			<channel id="currentalbum" typeId="currentalbum" />
			<channel id="currentartist" typeId="currentartist" />
			<channel id="currenttitle" typeId="currenttitle" />
			<channel id="currenttrack" typeId="currenttrack" />
			<channel id="led" typeId="led" />
			<channel id="linein" typeId="linein" />
			<channel id="localcoordinator" typeId="localcoordinator" />
			<channel id="mute" typeId="mute" />
			<channel id="playlinein" typeId="playlinein" />
			<channel id="playlist" typeId="playlist" />
			<channel id="playqueue" typeId="playqueue" />			
			<channel id="playtrack" typeId="playtrack" />			
			<channel id="playuri" typeId="playuri" />
			<channel id="publicaddress" typeId="publicaddress" />
			<channel id="radio" typeId="radio" />
			<channel id="remove" typeId="remove" />
			<channel id="restore" typeId="restore" />
			<channel id="restoreall" typeId="restoreall" />
			<channel id="save" typeId="save" />
			<channel id="saveall" typeId="saveall" />
			<channel id="snooze" typeId="snooze" />
			<channel id="standalone" typeId="standalone" />
			<channel id="state" typeId="state" />
			<channel id="stop" typeId="stop" />
			<channel id="volume" typeId="volume" />
			<channel id="zonegroup" typeId="zonegroup" />
			<channel id="zonegroupid" typeId="zonegroupid" />
			<channel id="zonename" typeId="zonename" />
		</channels>

		<config-description>
			<parameter name="udn" type="text">
				<label>Unique Device Name</label>
				<description>The UDN identifies the Zone Player.</description>
				<required>true</required>
			</parameter>

			<parameter name="refresh" type="integer">
				<label>Refresh interval</label>
				<description>Specifies the refresh interval in seconds</description>
				<default>60</default>
			</parameter>

		</config-description>
	</thing-type>

	<channel-type id="add" advanced="true">
		<item-type>String</item-type>
		<label>Add</label>
		<description>Add a Zone Player to the group of the given Zone Player</description>
	</channel-type>

	<channel-type id="alarm" advanced="true">
		<item-type>Switch</item-type>
		<label>Set Alarm</label>
		<description>Set the first occurring alarm either ON or OFF. Alarms have first have to be defined through the Sonos Controller app</description>
	</channel-type>

	<channel-type id="alarmproperties" advanced="true">
		<item-type>String</item-type>
		<label>Alarm Properties</label>
		<description>Properties of the alarm currently running</description>
	</channel-type>

	<channel-type id="alarmrunning" advanced="true">
		<item-type>Switch</item-type>
		<label>Alarm is running</label>
		<description>Set to ON if the alarm was triggered</description>
	</channel-type>

	<channel-type id="control">
		<item-type>Player</item-type>
		<label>Control</label>
		<description>Control the Zone Player, e.g. start/stop/next/previous/ffward/rewind</description>
		<category>Player</category>
	</channel-type>
	
		<channel-type id="currentalbum">
		<item-type>String</item-type>
		<label>Current Album</label>
		<description>Name of the album currently playing</description>
	</channel-type>

	<channel-type id="currentartist">
		<item-type>String</item-type>
		<label>Current Artist</label>
		<description>Name of the artist currently playing</description>
	</channel-type>

	<channel-type id="currenttitle">
		<item-type>String</item-type>
		<label>Current Title</label>
		<description>Title of the song currently playing</description>
	</channel-type>

	<channel-type id="currenttrack" advanced="true">
		<item-type>String</item-type>
		<label>Current Track</label>
		<description>Name of the current track or radio station currently playing</description>
	</channel-type>

	<channel-type id="led" advanced="true">
		<item-type>Switch</item-type>
		<label>Led</label>
		<description>Set or get the status of the white led on the front of the Zone Player </description>
	</channel-type>

	<channel-type id="linein" advanced="true">
		<item-type>Switch</item-type>
		<label>Line-in connected</label>
		<description>Indicator set to ON when the line-in of the Zone Player is connected</description>
	</channel-type>

	<channel-type id="localcoordinator" advanced="true">
		<item-type>Switch</item-type>
		<label>Local Coordinator</label>
		<description>Indicator set to ON if the this Zone Player is the Zone Group Coordinator</description>
	</channel-type>

	<channel-type id="mute" advanced="true">
		<item-type>Switch</item-type>
		<label>Mute</label>
		<description>Set or get the mute state of the master volume of the Zone Player</description>
	</channel-type>

	<channel-type id="playlinein" advanced="true">
		<item-type>String</item-type>
		<label>Play Line-in</label>
		<description>Play the Line-in of the the Zone Player corresponding to the given UIN</description>
	</channel-type>

	<channel-type id="playlist" advanced="true">
		<item-type>String</item-type>
		<label>Play Playlist</label>
		<description>Play the given playlist. The playlist has to predefined in the Sonos Controller app</description>
	</channel-type>

	<channel-type id="playqueue" advanced="true">
		<item-type>Switch</item-type>
		<label>Play Queue</label>
		<description>Play the songs from the current queue</description>
	</channel-type>

	<channel-type id="playtrack" advanced="true">
		<item-type>Number</item-type>
		<label>Play Track</label>
		<description>Play the given track number from the current queue</description>
	</channel-type>	
	
	<channel-type id="playuri" advanced="true">
		<item-type>String</item-type>
		<label>Play URI</label>
		<description>Play the given URI</description>
	</channel-type>

	<channel-type id="publicaddress" advanced="true">
		<item-type>Switch</item-type>
		<label>Public Address</label>
		<description>Put all Zone Players in one group, and stream audio from the line-in from the Zone Player that triggered the command</description>
	</channel-type>

	<channel-type id="radio" advanced="true">
		<item-type>String</item-type>
		<label>Radio</label>
		<description>Play the given radio station. The radio station has to be predefined in the Sonos Controller app</description>
	</channel-type>

	<channel-type id="remove" advanced="true">
		<item-type>String</item-type>
		<label>Remove</label>
		<description>Remove the given Zone Player to the group of this Zone Player</description>
	</channel-type>

	<channel-type id="restore" advanced="true">
		<item-type>Switch</item-type>
		<label>Restore</label>
		<description>Restore the state of the Zone Player</description>
	</channel-type>

	<channel-type id="restoreall" advanced="true">
		<item-type>Switch</item-type>
		<label>Restore All</label>
		<description>Restore the state of all the Zone Players</description>
	</channel-type>

	<channel-type id="save" advanced="true">
		<item-type>Switch</item-type>
		<label>Save</label>
		<description>Save the state of the Zone Player</description>
	</channel-type>

	<channel-type id="saveall" advanced="true">
		<item-type>Switch</item-type>
		<label>Save All</label>
		<description>Save the state of all the Zone Players</description>
	</channel-type>

	<channel-type id="snooze" advanced="true">
		<item-type>Number</item-type>
		<label>Snooze</label>
		<description>Snooze the running alarm, if any, with the given number of minutes</description>
	</channel-type>

	<channel-type id="standalone" advanced="true">
		<item-type>Switch</item-type>
		<label>Stand Alone</label>
		<description>Make the Zone Player leave its Group and become a standalone Zone Player</description>
	</channel-type>

	<!-- The Sonos State Type -->
	<channel-type id="state" advanced="true">
		<item-type>String</item-type>
		<label>State</label>
		<description>The State channel contains state of the Zone Player, e.g. PLAYING, STOPPED,...</description>
	</channel-type>

	<channel-type id="stop" advanced="true">
		<item-type>Switch</item-type>
		<label>Stop</label>
		<description>Stop the Zone Player</description>
	</channel-type>

	<channel-type id="volume">
		<item-type>Dimmer</item-type>
		<label>Volume</label>
		<description>Set or get the master volume</description>
		<category>SoundVolume</category>
	</channel-type>

	<channel-type id="zonegroup" advanced="true">
		<item-type>String</item-type>
		<label>Zone Group</label>
		<description>XML formatted string with the current zonegroup configuration</description>
	</channel-type>

	<channel-type id="zonegroupid" advanced="true">
		<item-type>String</item-type>
		<label>Zone Group ID</label>
		<description>Id of the Zone Group the Zone Player belongs to</description>
	</channel-type>

	<channel-type id="zonename" advanced="true">
		<item-type>String</item-type>
		<label>Zone Name</label>
		<description>Name of the Zone Group the Zone Player belongs to</description>
	</channel-type>

</thing:thing-descriptions>
