<?xml version="1.0" encoding="UTF-8"?>
<thing:thing-descriptions bindingId="zigbee"
    xmlns:xsi="http://www.w3.org/2001/XMLSchema-instance"
    xmlns:thing="http://eclipse.org/smarthome/schemas/thing-description/v1.0.0"
    xsi:schemaLocation="http://eclipse.org/smarthome/schemas/thing-description/v1.0.0 http://eclipse.org/smarthome/schemas/thing-description-1.0.0.xsd">

    <!-- Color Channel -->
    <channel-type id="color_color">
        <item-type>Color</item-type>
        <label>Color</label>
        <description>The color channel allows to control the color of a light.
            It is also possible to dim values and switch the light on and off.
        </description>
        <category>ColorLight</category>
    </channel-type>

    <!-- Color Temperature Channel -->
    <channel-type id="color_temperature">
        <item-type>Dimmer</item-type>
        <label>Color Temperature</label>
        <description>The color temperature channel allows to set the color
            temperature of a light from 0 (cold) to 100 (warm).</description>
        <category>ColorLight</category>
    </channel-type>

    <!-- Temperature Channel -->
    <channel-type id="measurement_temperature">
        <item-type>Number</item-type>
        <label>Temperature</label>
        <description>Indicates the current temperature</description>
        <category>Temperature</category>
        <state pattern="%0.1f" readOnly="true">
        </state>
        <config-description>
            <parameter name="config_scale" type="text">
                <label>Scale</label>
                <description>Select the scale for temperature readings</description>
                <default>0</default>
                <options>
                    <option value="0">Celsius</option>
                    <option value="1">Fahrenheit</option>
                </options>
            </parameter>
        </config-description>
    </channel-type>

    <!-- Humidity Channel -->
    <channel-type id="measurement_relativehumidity">
        <item-type>Number</item-type>
        <label>Humidity</label>
        <description>Indicates the current relative humidity</description>
        <category>Humidity</category>
        <state pattern="%0.1f" readOnly="true">
        </state>
    </channel-type>

    <!-- On Off Switch -->
    <channel-type id="switch_onoff">
        <item-type>Number</item-type>
        <label>Switch</label>
        <description>Switches the power on and off</description>
        <category>Light</category>
        <state readOnly="true">
            <options>
                <option value="ON">On</option>
                <option value="OFF">Off</option>
            </options>
        </state>
    </channel-type>

    <!-- Dimmer Switch -->
    <channel-type id="switch_dimmer">
        <item-type>Dimmer</item-type>
        <label>Dimmer</label>
        <description>Sets the level of the light</description>
        <category>Light</category>
    </channel-type>

</thing:thing-descriptions>